ofdc_tollkit/__init__.py
ofdc_tollkit/functions.py
ofdc_tollkit-0.1.4.dist-info/METADATA
ofdc_tollkit-0.1.4.dist-info/WHEEL
ofdc_tollkit-0.1.4.dist-info/RECORD
